MANIFEST.in
README.rst
md2remark_runner.py
setup.py
md2remark/__init__.py
md2remark/main.py
md2remark.egg-info/PKG-INFO
md2remark.egg-info/SOURCES.txt
md2remark.egg-info/dependency_links.txt
md2remark.egg-info/entry_points.txt
md2remark.egg-info/requires.txt
md2remark.egg-info/top_level.txt
md2remark/resources/__init__.py
md2remark/resources/templates/__init__.py
md2remark/resources/templates/slideshow.mustache