Metadata-Version: 1.1
Name: md2remark
Version: 0.1.0
Summary: Builds a slideshow from markdown using remark.js.
Home-page: https://github.com/patrickayoup/md2remark/
Author: Patrick Ayoup
Author-email: patrick.ayoup@gmail.com
License: MIT
Download-URL: https://github.com/patrickayoup/md2remark/tarball/0.1.0
Keywords: markdown,slideshow
Platform: UNKNOWN
Classifier: Development Status :: 5 - Production/Stable
Classifier: Environment :: Console
Classifier: Intended Audience :: Developers
Classifier: Intended Audience :: End Users/Desktop
Classifier: License :: OSI Approved :: MIT License
Classifier: Operating System :: OS Independent
Classifier: Topic :: Utilities
